deque.py
queue-ayp.py
stack.py
ayp_stack-0.0.1.dist-info/METADATA
ayp_stack-0.0.1.dist-info/WHEEL
ayp_stack-0.0.1.dist-info/licenses/LICENSE
ayp_stack-0.0.1.dist-info/RECORD
