Metadata-Version: 2.1
Name: ayp-stack
Version: 0.0.1
Summary: paquetes pilas colas y dipolos
Project-URL: Homepage, https://github.com/memeoDev/ayp-stack
Project-URL: Bug Tracker, https://github.com/memeoDev/ayp-stack/issues
Author-email: memeoAmazonas <jgot.universidad@gmail.com>
License: MIT License
License-File: LICENSE
Classifier: License :: OSI Approved :: MIT License
Classifier: Operating System :: OS Independent
Classifier: Programming Language :: Python :: 3
Requires-Python: >=3.3
